iris_recognizer_system/__init__.py
iris_recognizer_system/iris_recognition.py
iris_recognizer_system-0.0.1.dist-info/LICENSE.md
iris_recognizer_system-0.0.1.dist-info/METADATA
iris_recognizer_system-0.0.1.dist-info/WHEEL
iris_recognizer_system-0.0.1.dist-info/top_level.txt
iris_recognizer_system-0.0.1.dist-info/RECORD
