Metadata-Version: 2.1
Name: iris_recognizer_system
Version: 0.0.1
Summary: Iris Recognizer System allows you to analyze iris images and compare them. Also it brings a database control.
Home-page: https://github.com/elymsyr/iris-recognition
Author: Orhun Eren Yalçınkaya
Author-email: orhun868@gmail.com
License: MIT
Classifier: Programming Language :: Python :: 3
Classifier: License :: OSI Approved :: MIT License
Classifier: Operating System :: OS Independent
License-File: LICENSE.md
Requires-Dist: asttokens ==2.4.1
Requires-Dist: certifi ==2024.7.4
Requires-Dist: charset-normalizer ==3.3.2
Requires-Dist: comm ==0.2.2
Requires-Dist: contourpy ==1.2.1
Requires-Dist: cycler ==0.12.1
Requires-Dist: debugpy ==1.8.5
Requires-Dist: decorator ==5.1.1
Requires-Dist: exceptiongroup ==1.2.2
Requires-Dist: executing ==2.0.1
Requires-Dist: fonttools ==4.53.1
Requires-Dist: idna ==3.8
Requires-Dist: importlib-metadata ==8.4.0
Requires-Dist: importlib-resources ==6.4.4
Requires-Dist: imutils ==0.5.4
Requires-Dist: ipykernel ==6.29.5
Requires-Dist: ipython ==8.18.1
Requires-Dist: jedi ==0.19.1
Requires-Dist: jupyter-client ==8.6.2
Requires-Dist: jupyter-core ==5.7.2
Requires-Dist: kiwisolver ==1.4.5
Requires-Dist: matplotlib ==3.9.2
Requires-Dist: matplotlib-inline ==0.1.7
Requires-Dist: nest-asyncio ==1.6.0
Requires-Dist: numpy ==2.0.2
Requires-Dist: opencv-python ==4.10.0.84
Requires-Dist: packaging ==24.1
Requires-Dist: parso ==0.8.4
Requires-Dist: pexpect ==4.9.0
Requires-Dist: pillow ==10.4.0
Requires-Dist: platformdirs ==4.2.2
Requires-Dist: prompt-toolkit ==3.0.47
Requires-Dist: psutil ==6.0.0
Requires-Dist: ptyprocess ==0.7.0
Requires-Dist: pure-eval ==0.2.3
Requires-Dist: Pygments ==2.18.0
Requires-Dist: pyparsing ==3.1.4
Requires-Dist: python-dateutil ==2.9.0.post0
Requires-Dist: pyzmq ==26.2.0
Requires-Dist: requests ==2.32.3
Requires-Dist: six ==1.16.0
Requires-Dist: stack-data ==0.6.3
Requires-Dist: tornado ==6.4.1
Requires-Dist: traitlets ==5.14.3
Requires-Dist: typing-extensions ==4.12.2
Requires-Dist: urllib3 ==2.2.2
Requires-Dist: wcwidth ==0.2.13
Requires-Dist: zipp ==3.20.1
